rdfizer/__init__.py
rdfizer/__main__.py
rdfizer/cc_functions.py
rdfizer/fnml_functions.py
rdfizer/functions.py
rdfizer/inner_functions.py
rdfizer/lv_functions.py
rdfizer/mapping_functions.py
rdfizer/semantify.py
rdfizer/triples_map/TriplesMap.py
rdfizer/triples_map/__init__.py
rdfizer-4.7.5.13.5.dist-info/METADATA
rdfizer-4.7.5.13.5.dist-info/WHEEL
rdfizer-4.7.5.13.5.dist-info/entry_points.txt
rdfizer-4.7.5.13.5.dist-info/top_level.txt
rdfizer-4.7.5.13.5.dist-info/RECORD
