Metadata-Version: 2.4
Name: rdfizer
Version: 4.7.5.13.5
Summary: This project presents the SDM-RDFizer, an interpreter of mapping rules that allows the transformation of (un)structured data into RDF knowledge graphs. The current version of the SDM-RDFizer assumes mapping rules are defined in the RDF Mapping Language (RML) by Dimou et al.
Home-page: https://github.com/SDM-TIB/SDM-RDFizer
Author: Maria-Esther Vidal
Author-email: maria.vidal@tib.eu
License: Apache 2.0
Classifier: Programming Language :: Python :: 3
Classifier: License :: OSI Approved :: Apache Software License
Classifier: Operating System :: OS Independent
Classifier: Development Status :: 5 - Production/Stable
Classifier: Environment :: Console
Classifier: Intended Audience :: Science/Research
Classifier: Topic :: Utilities
Classifier: Topic :: Software Development :: Pre-processors
Classifier: Topic :: Scientific/Engineering :: Interface Engine/Protocol Translator
Requires-Python: >=3.6
Requires-Dist: Flask
Requires-Dist: isodate>=0.6.0
Requires-Dist: pyparsing>=2.2.0
Requires-Dist: rdflib
Requires-Dist: six>=1.11.0
Requires-Dist: mysql-connector-python>=8.0.22
Requires-Dist: psycopg2-binary
Requires-Dist: pandas
Requires-Dist: requests
Requires-Dist: sparqlwrapper
Requires-Dist: pyodbc
Requires-Dist: jsonpath-ng
Dynamic: author
Dynamic: author-email
Dynamic: classifier
Dynamic: description
Dynamic: description-content-type
Dynamic: home-page
Dynamic: license
Dynamic: requires-dist
Dynamic: requires-python
Dynamic: summary
